README.md
setup.cfg
setup.py
datepickerwidget/__init__.py
datepickerwidget/widgets.py
datepickerwidget.egg-info/PKG-INFO
datepickerwidget.egg-info/SOURCES.txt
datepickerwidget.egg-info/dependency_links.txt
datepickerwidget.egg-info/not-zip-safe
datepickerwidget.egg-info/requires.txt
datepickerwidget.egg-info/top_level.txt
datepickerwidget/locale/en/LC_MESSAGES/django.mo
datepickerwidget/locale/en/LC_MESSAGES/django.po
datepickerwidget/locale/it/LC_MESSAGES/django.mo
datepickerwidget/locale/it/LC_MESSAGES/django.po
datepickerwidget/static/css/bootstrap-datetimepicker.css
datepickerwidget/static/css/datetimepicker.css
datepickerwidget/static/js/bootstrap-datetimepicker.js
datepickerwidget/static/js/locales/bootstrap-datetimepicker.ar.js
datepickerwidget/static/js/locales/bootstrap-datetimepicker.bg.js
datepickerwidget/static/js/locales/bootstrap-datetimepicker.ca.js
datepickerwidget/static/js/locales/bootstrap-datetimepicker.cs.js
datepickerwidget/static/js/locales/bootstrap-datetimepicker.da.js
datepickerwidget/static/js/locales/bootstrap-datetimepicker.de.js
datepickerwidget/static/js/locales/bootstrap-datetimepicker.ee.js
datepickerwidget/static/js/locales/bootstrap-datetimepicker.el.js
datepickerwidget/static/js/locales/bootstrap-datetimepicker.es.js
datepickerwidget/static/js/locales/bootstrap-datetimepicker.fi.js
datepickerwidget/static/js/locales/bootstrap-datetimepicker.fr.js
datepickerwidget/static/js/locales/bootstrap-datetimepicker.he.js
datepickerwidget/static/js/locales/bootstrap-datetimepicker.hr.js
datepickerwidget/static/js/locales/bootstrap-datetimepicker.hu.js
datepickerwidget/static/js/locales/bootstrap-datetimepicker.id.js
datepickerwidget/static/js/locales/bootstrap-datetimepicker.is.js
datepickerwidget/static/js/locales/bootstrap-datetimepicker.it.js
datepickerwidget/static/js/locales/bootstrap-datetimepicker.ja.js
datepickerwidget/static/js/locales/bootstrap-datetimepicker.ko.js
datepickerwidget/static/js/locales/bootstrap-datetimepicker.kr.js
datepickerwidget/static/js/locales/bootstrap-datetimepicker.lt.js
datepickerwidget/static/js/locales/bootstrap-datetimepicker.lv.js
datepickerwidget/static/js/locales/bootstrap-datetimepicker.ms.js
